pyplasm/__init__.py
pyplasm/_xgepy.so
pyplasm/fenvs.py
pyplasm/selftest
pyplasm/setup.py
pyplasm/viewer.py
pyplasm/xgepy.py
pyplasm/examples/arm2d.py
pyplasm/examples/ashtray.py
pyplasm/examples/ballorganizer.py
pyplasm/examples/basic.py
pyplasm/examples/batch.py
pyplasm/examples/bsp.py
pyplasm/examples/colors.py
pyplasm/examples/graph.py
pyplasm/examples/lathering.py
pyplasm/examples/load_obj.obj
pyplasm/examples/load_obj.py
pyplasm/examples/pisa.py
pyplasm/examples/plasm.py
pyplasm/examples/rotational_solid.py
pyplasm/examples/sphere.obj
pyplasm/examples/temple.py
pyplasm/examples/threecubes.py
pyplasm/examples/broken/manipulator.py
pyplasm-3.0.21.dist-info/METADATA
pyplasm-3.0.21.dist-info/WHEEL
pyplasm-3.0.21.dist-info/top_level.txt
pyplasm-3.0.21.dist-info/RECORD
