Metadata-Version: 2.1
Name: pyplasm
Version: 3.0.21
Summary: Plasm is a design language for geometric and solid parametric design, developed by the CAD Group at the Universities La Sapienza and Roma Tre in Italy
Home-page: https://github.com/plasm-language/pyplasm
Author: Giorgio Scorzelli
Author-email: scorzell@dia.uniroma3.it
License: GPL
Platform: Linux
Platform: OS-X
Platform: Windows
